awsService/__init__.py
awsService/comprehend.py
awsService/helper.py
awsService/medicalComprehend.py
vLifeCloudApi-0.0.1.dist-info/LICENSE.txt
vLifeCloudApi-0.0.1.dist-info/METADATA
vLifeCloudApi-0.0.1.dist-info/WHEEL
vLifeCloudApi-0.0.1.dist-info/top_level.txt
vLifeCloudApi-0.0.1.dist-info/RECORD
