Metadata-Version: 2.1
Name: vLifeCloudApi
Version: 0.0.1
Summary: vLife Support API for AWS Service
Author: Gopinath Muthusamy
Author-email: gopinathmu@virtusa.com
Classifier: Programming Language :: Python :: 3
Classifier: License :: OSI Approved :: MIT License
Classifier: Operating System :: OS Independent
Requires-Python: >=3.6
License-File: LICENSE.txt
Requires-Dist: boto3
Requires-Dist: numpy
